[
{"country": "guinea-bissau", "years": []},
{"country": "honduras", "years": [{"year": 2003}, {"year": 2002}, {"year": 2001}, {"year": 2000}, {"year": 1999}, {"year": 1998}, {"year": 1996}, {"year": 1995}]},
{"country": "fiji", "years": [{"year": 2015}, {"year": 2007}, {"year": 2006}, {"year": 2004}, {"year": 2003}, {"year": 2001}, {"year": 2000}, {"year": 1996}, {"year": 1995}, {"year": 1994}, {"year": 1993}, {"year": 1992}]},
{"country": "jordan", "years": [{"year": 2007}, {"year": 2005}, {"year": 2004}, {"year": 2003}, {"year": 2002}, {"year": 2001}, {"year": 2000}, {"year": 1999}, {"year": 1997}, {"year": 1995}, {"year": 1993}]},
{"country": "sao-tome-and-principe", "years": [{"year": 2001}, {"year": 1999}]},
{"country": "kenya", "years": [{"year": 2007}, {"year": 2006}, {"year": 2005}, {"year": 2002}, {"year": 2001}, {"year": 2000}, {"year": 1993}]},
{"country": "saudi-arabia", "years": []},
{"country": "austria", "years": [{"year": 2019}, {"year": 2018}, {"year": 2015}, {"year": 2014}, {"year": 2013}, {"year": 2012}, {"year": 2010}, {"year": 2009}, {"year": 2008}, {"year": 2007}, {"year": 2006}, {"year": 2005}, {"year": 2004}, {"year": 2003}, {"year": 2002}, {"year": 2001}, {"year": 2000}, {"year": 1999}, {"year": 1998}, {"year": 1997}, {"year": 1996}, {"year": 1995}, {"year": 1994}, {"year": 1993}, {"year": 1992}]},
{"country": "timor-leste", "years": [{"year": 2002}]},
{"country": "republic-of-korea", "years": [{"year": 2022}, {"year": 2021}, {"year": 2020}, {"year": 2019}, {"year": 2018}, {"year": 2017}, {"year": 2016}, {"year": 2015}, {"year": 2014}, {"year": 2013}, {"year": 2012}, {"year": 2011}, {"year": 2010}, {"year": 2009}, {"year": 2008}, {"year": 2007}, {"year": 2006}, {"year": 2005}, {"year": 2004}, {"year": 2003}, {"year": 2002}, {"year": 2001}, {"year": 2000}, {"year": 1999}, {"year": 1998}, {"year": 1997}, {"year": 1996}, {"year": 1995}, {"year": 1994}, {"year": 1993}, {"year": 1992}]},
{"country": "costa-rica", "years": [{"year": 2008}, {"year": 2006}, {"year": 2005}, {"year": 2004}, {"year": 2003}, {"year": 2002}, {"year": 2001}, {"year": 2000}, {"year": 1999}, {"year": 1998}]},
{"country": "hungary", "years": [{"year": 2021}, {"year": 2019}, {"year": 2018}, {"year": 2017}, {"year": 2016}, {"year": 2015}, {"year": 2014}, {"year": 2013}, {"year": 2012}, {"year": 2011}, {"year": 2010}, {"year": 2009}, {"year": 2008}, {"year": 2007}, {"year": 2006}, {"year": 2005}, {"year": 2004}, {"year": 2003}, {"year": 2002}, {"year": 2001}, {"year": 2000}, {"year": 1999}, {"year": 1998}, {"year": 1997}, {"year": 1996}, {"year": 1995}, {"year": 1994}, {"year": 1993}, {"year": 1992}]},
{"country": "federated-states-of-micronesia", "years": [{"year": 2006}, {"year": 2005}, {"year": 2004}, {"year": 2003}, {"year": 2002}, {"year": 2000}, {"year": 1997}]},
{"country": "sierra-leone", "years": [{"year": 2021}, {"year": 2006}, {"year": 2005}, {"year": 2002}, {"year": 2001}, {"year": 1993}]},
{"country": "peru", "years": [{"year": 2021}, {"year": 2019}, {"year": 2018}, {"year": 2010}, {"year": 2009}, {"year": 2008}, {"year": 2004}, {"year": 2003}, {"year": 2002}, {"year": 2001}, {"year": 2000}, {"year": 1999}, {"year": 1998}, {"year": 1997}, {"year": 1996}, {"year": 1995}, {"year": 1994}, {"year": 1993}, {"year": 1992}]},
{"country": "united-states", "years": [{"year": 2020}, {"year": 2019}, {"year": 2018}, {"year": 2017}, {"year": 2016}, {"year": 2015}, {"year": 2014}, {"year": 2013}, {"year": 2012}, {"year": 2011}, {"year": 2010}, {"year": 2009}, {"year": 2008}, {"year": 2007}, {"year": 2006}, {"year": 2005}, {"year": 2004}, {"year": 2003}, {"year": 2002}, {"year": 2001}, {"year": 2000}, {"year": 1999}, {"year": 1998}, {"year": 1997}, {"year": 1996}, {"year": 1995}, {"year": 1994}, {"year": 1993}, {"year": 1992}]},
{"country": "belize", "years": [{"year": 2010}, {"year": 2008}, {"year": 2007}, {"year": 2006}, {"year": 2005}, {"year": 2004}, {"year": 2003}, {"year": 2002}, {"year": 2001}, {"year": 2000}, {"year": 1999}, {"year": 1997}, {"year": 1996}, {"year": 1994}]},
{"country": "palau", "years": [{"year": 2021}, {"year": 2010}, {"year": 2007}, {"year": 2006}, {"year": 2005}, {"year": 2004}, {"year": 2003}, {"year": 2002}, {"year": 2001}, {"year": 2000}]},
{"country": "suriname", "years": [{"year": 2020}, {"year": 2019}, {"year": 2018}, {"year": 2017}, {"year": 2010}, {"year": 2008}, {"year": 2007}, {"year": 2006}, {"year": 2005}, {"year": 2003}, {"year": 2002}, {"year": 2001}, {"year": 2000}, {"year": 1999}]},
{"country": "tonga", "years": [{"year": 2006}, {"year": 2004}, {"year": 2003}, {"year": 2000}]},
{"country": "myanmar", "years": []},
{"country": "guyana", "years": [{"year": 2010}, {"year": 2005}, {"year": 2004}, {"year": 2003}, {"year": 2001}, {"year": 2000}, {"year": 1999}, {"year": 1997}, {"year": 1996}, {"year": 1994}]},
{"country": "australia", "years": [{"year": 2021}, {"year": 2020}, {"year": 2019}, {"year": 2018}, {"year": 2017}, {"year": 2013}, {"year": 2012}, {"year": 2011}, {"year": 2010}, {"year": 2009}, {"year": 2008}, {"year": 2007}, {"year": 2006}, {"year": 2005}, {"year": 2004}, {"year": 2003}, {"year": 2002}, {"year": 2001}, {"year": 2000}, {"year": 1999}, {"year": 1998}, {"year": 1997}, {"year": 1996}, {"year": 1995}, {"year": 1994}, {"year": 1993}, {"year": 1992}]},
{"country": "germany", "years": [{"year": 2022}, {"year": 2021}, {"year": 2020}, {"year": 2019}, {"year": 2018}, {"year": 2017}, {"year": 2016}, {"year": 2015}, {"year": 2014}, {"year": 2013}, {"year": 2012}, {"year": 2011}, {"year": 2010}, {"year": 2009}, {"year": 2008}, {"year": 2007}, {"year": 2006}, {"year": 2005}, {"year": 2004}, {"year": 2003}, {"year": 2002}, {"year": 2001}, {"year": 2000}, {"year": 1999}, {"year": 1998}, {"year": 1997}, {"year": 1996}, {"year": 1995}, {"year": 1994}, {"year": 1993}, {"year": 1992}]},
{"country": "senegal", "years": [{"year": 2017}, {"year": 2015}, {"year": 2006}, {"year": 2005}, {"year": 2004}, {"year": 2003}, {"year": 2002}, {"year": 2001}, {"year": 1992}]},
{"country": "malaysia", "years": [{"year": 2021}, {"year": 2012}, {"year": 2011}, {"year": 2010}, {"year": 2009}, {"year": 2008}, {"year": 2006}, {"year": 2005}, {"year": 2004}, {"year": 2003}, {"year": 2002}, {"year": 2001}, {"year": 2000}, {"year": 1999}, {"year": 1998}, {"year": 1997}, {"year": 1996}, {"year": 1995}, {"year": 1994}, {"year": 1993}, {"year": 1992}]},
{"country": "grenada", "years": [{"year": 2014}, {"year": 2013}, {"year": 2012}, {"year": 2010}, {"year": 2008}, {"year": 2007}, {"year": 2005}, {"year": 2004}, {"year": 2002}, {"year": 2001}, {"year": 2000}, {"year": 1999}, {"year": 1996}, {"year": 1994}, {"year": 1993}, {"year": 1992}]},
{"country": "south-africa", "years": [{"year": 2022}, {"year": 2021}, {"year": 2018}, {"year": 2017}, {"year": 2016}, {"year": 2013}, {"year": 2012}, {"year": 2009}, {"year": 2008}, {"year": 2007}, {"year": 2006}, {"year": 2005}, {"year": 2004}, {"year": 2003}, {"year": 2002}, {"year": 2001}, {"year": 2000}, {"year": 1999}, {"year": 1998}, {"year": 1997}, {"year": 1996}, {"year": 1995}, {"year": 1994}, {"year": 1992}]},
{"country": "israel", "years": [{"year": 2022}, {"year": 2021}, {"year": 2020}, {"year": 2019}, {"year": 2018}, {"year": 2017}, {"year": 2016}, {"year": 2015}, {"year": 2014}, {"year": 2011}, {"year": 2009}, {"year": 2008}, {"year": 2007}, {"year": 2006}, {"year": 2005}, {"year": 2004}, {"year": 2003}, {"year": 2002}, {"year": 2001}, {"year": 2000}, {"year": 1999}, {"year": 1998}, {"year": 1997}, {"year": 1996}, {"year": 1995}, {"year": 1994}, {"year": 1993}, {"year": 1992}]},
{"country": "angola", "years": []},
{"country": "dominica", "years": [{"year": 2001}, {"year": 1999}, {"year": 1995}, {"year": 1994}, {"year": 1993}, {"year": 1992}]},
{"country": "lithuania", "years": [{"year": 2022}, {"year": 2021}, {"year": 2020}, {"year": 2019}, {"year": 2018}, {"year": 2017}, {"year": 2016}, {"year": 2015}, {"year": 2014}, {"year": 2013}, {"year": 2012}, {"year": 2011}, {"year": 2010}, {"year": 2009}, {"year": 2008}, {"year": 2007}, {"year": 2006}, {"year": 2005}, {"year": 2004}, {"year": 2003}, {"year": 2002}, {"year": 2001}, {"year": 2000}, {"year": 1999}, {"year": 1998}, {"year": 1997}, {"year": 1996}, {"year": 1995}, {"year": 1992}]},
{"country": "uzbekistan", "years": [{"year": 2003}, {"year": 2001}, {"year": 2000}, {"year": 1999}]},
{"country": "slovakia", "years": [{"year": 2021}, {"year": 2020}, {"year": 2018}, {"year": 2017}, {"year": 2016}, {"year": 2015}, {"year": 2014}, {"year": 2013}, {"year": 2012}, {"year": 2011}, {"year": 2010}, {"year": 2009}, {"year": 2008}, {"year": 2007}, {"year": 2006}, {"year": 2005}, {"year": 2004}, {"year": 2003}, {"year": 2002}, {"year": 2001}, {"year": 2000}, {"year": 1999}, {"year": 1998}, {"year": 1997}, {"year": 1996}, {"year": 1995}, {"year": 1994}, {"year": 1993}, {"year": 1992}]},
{"country": "lebanon", "years": [{"year": 2013}, {"year": 2010}, {"year": 2009}, {"year": 2008}, {"year": 2007}, {"year": 2006}, {"year": 2005}, {"year": 2004}, {"year": 2003}, {"year": 2002}, {"year": 2001}, {"year": 1992}]},
{"country": "south-sudan", "years": []},
{"country": "montenegro", "years": [{"year": 2020}, {"year": 2016}, {"year": 2014}, {"year": 2007}]},
{"country": "seychelles", "years": [{"year": 2008}, {"year": 2006}, {"year": 2005}, {"year": 2004}, {"year": 2002}, {"year": 2001}, {"year": 2000}, {"year": 1999}, {"year": 1997}, {"year": 1996}, {"year": 1992}]},
{"country": "bulgaria", "years": [{"year": 2022}, {"year": 2021}, {"year": 2020}, {"year": 2019}, {"year": 2018}, {"year": 2017}, {"year": 2016}, {"year": 2015}, {"year": 2014}, {"year": 2013}, {"year": 2012}, {"year": 2011}, {"year": 2010}, {"year": 2009}, {"year": 2008}, {"year": 2007}, {"year": 2006}, {"year": 2005}, {"year": 2004}, {"year": 2003}, {"year": 2002}, {"year": 2001}, {"year": 2000}, {"year": 1999}, {"year": 1998}, {"year": 1997}, {"year": 1996}, {"year": 1995}, {"year": 1994}, {"year": 1993}, {"year": 1992}]},
{"country": "qatar", "years": [{"year": 1999}, {"year": 1997}, {"year": 1992}]},
{"country": "france", "years": [{"year": 2021}, {"year": 2020}, {"year": 2019}, {"year": 2017}, {"year": 2016}, {"year": 2014}, {"year": 2012}, {"year": 2011}, {"year": 2008}, {"year": 2007}, {"year": 2006}, {"year": 2005}, {"year": 2004}, {"year": 2003}, {"year": 2002}, {"year": 2001}, {"year": 2000}, {"year": 1999}, {"year": 1998}, {"year": 1997}, {"year": 1996}, {"year": 1995}, {"year": 1994}, {"year": 1993}, {"year": 1992}]},
{"country": "bahrain", "years": []},
{"country": "oman", "years": [{"year": 1992}]},
{"country": "norway", "years": [{"year": 2021}, {"year": 2014}, {"year": 2013}, {"year": 2012}, {"year": 2011}, {"year": 2010}, {"year": 2009}, {"year": 2008}, {"year": 2007}, {"year": 2006}, {"year": 2005}, {"year": 2004}, {"year": 2003}, {"year": 2002}, {"year": 2001}, {"year": 2000}, {"year": 1999}, {"year": 1998}, {"year": 1997}, {"year": 1996}, {"year": 1995}, {"year": 1994}, {"year": 1993}, {"year": 1992}]},
{"country": "serbia", "years": [{"year": 2022}, {"year": 2021}, {"year": 2017}, {"year": 2016}, {"year": 2015}, {"year": 2014}, {"year": 2013}, {"year": 2012}, {"year": 2010}, {"year": 2009}, {"year": 2007}, {"year": 2006}, {"year": 2004}, {"year": 2003}, {"year": 2002}, {"year": 2001}, {"year": 1994}, {"year": 1993}, {"year": 1992}]},
{"country": "rwanda", "years": [{"year": 2001}]},
{"country": "mexico", "years": [{"year": 2021}, {"year": 2015}, {"year": 2014}, {"year": 2013}, {"year": 2012}, {"year": 2011}, {"year": 2010}, {"year": 2009}, {"year": 2008}, {"year": 2007}, {"year": 2006}, {"year": 2005}, {"year": 2004}, {"year": 2003}, {"year": 2002}, {"year": 2001}, {"year": 2000}, {"year": 1998}, {"year": 1996}, {"year": 1995}, {"year": 1994}, {"year": 1993}, {"year": 1992}]},
{"country": "libya", "years": [{"year": 1997}, {"year": 1994}, {"year": 1992}]},
{"country": "the-former-yugoslav-republic-of-macedonia", "years": [{"year": 2017}, {"year": 2015}, {"year": 2014}, {"year": 2012}, {"year": 2011}, {"year": 2010}, {"year": 2009}, {"year": 2008}, {"year": 2007}, {"year": 2006}, {"year": 2005}, {"year": 2003}, {"year": 2002}, {"year": 2001}, {"year": 2000}, {"year": 1999}, {"year": 1997}, {"year": 1996}]},
{"country": "el-salvador", "years": [{"year": 2015}, {"year": 2014}, {"year": 2013}, {"year": 2012}, {"year": 2011}, {"year": 2010}, {"year": 2007}, {"year": 2006}, {"year": 2003}, {"year": 1994}]},
{"country": "iceland", "years": [{"year": 2013}, {"year": 2012}, {"year": 2011}, {"year": 2010}, {"year": 2009}, {"year": 2008}, {"year": 2007}, {"year": 2006}, {"year": 2005}, {"year": 2004}, {"year": 2003}, {"year": 2002}, {"year": 2001}, {"year": 2000}, {"year": 1999}, {"year": 1998}, {"year": 1997}, {"year": 1996}, {"year": 1995}, {"year": 1994}, {"year": 1993}, {"year": 1992}]},
{"country": "mozambique", "years": [{"year": 2011}, {"year": 2006}, {"year": 2005}, {"year": 2004}]},
{"country": "mongolia", "years": [{"year": 2014}, {"year": 2010}, {"year": 2007}, {"year": 2006}, {"year": 2005}, {"year": 2004}, {"year": 2001}, {"year": 2000}, {"year": 1999}, {"year": 1998}, {"year": 1997}, {"year": 1996}, {"year": 1995}, {"year": 1994}, {"year": 1993}, {"year": 1992}]},
{"country": "mauritius", "years": [{"year": 2019}, {"year": 2018}, {"year": 2012}, {"year": 2009}, {"year": 2007}, {"year": 2005}, {"year": 2004}, {"year": 2003}, {"year": 2002}, {"year": 2001}, {"year": 2000}, {"year": 1999}, {"year": 1997}, {"year": 1996}, {"year": 1995}, {"year": 1994}, {"year": 1993}, {"year": 1992}]},
{"country": "egypt", "years": [{"year": 1992}]},
{"country": "eritrea", "years": []},
{"country": "antigua-and-barbuda", "years": [{"year": 2021}, {"year": 2009}, {"year": 2008}, {"year": 2007}, {"year": 2006}, {"year": 2005}, {"year": 2003}, {"year": 2002}, {"year": 2001}, {"year": 2000}, {"year": 1997}, {"year": 1993}, {"year": 1992}]},
{"country": "islamic-republic-of-iran", "years": [{"year": 1998}, {"year": 1996}, {"year": 1995}, {"year": 1994}, {"year": 1993}, {"year": 1992}]},
{"country": "vanuatu", "years": [{"year": 2015}, {"year": 2005}, {"year": 2004}, {"year": 2002}, {"year": 2001}, {"year": 2000}, {"year": 1995}, {"year": 1994}, {"year": 1993}, {"year": 1992}]},
{"country": "tajikistan", "years": [{"year": 2009}, {"year": 2008}, {"year": 2007}, {"year": 2006}, {"year": 2005}, {"year": 2004}, {"year": 2003}, {"year": 2001}, {"year": 1998}, {"year": 1997}, {"year": 1995}, {"year": 1994}]},
{"country": "singapore", "years": [{"year": 2021}, {"year": 2020}, {"year": 2019}, {"year": 2018}, {"year": 2017}, {"year": 2016}, {"year": 2015}, {"year": 2014}, {"year": 2012}, {"year": 2011}, {"year": 2010}, {"year": 2009}, {"year": 2008}, {"year": 2007}, {"year": 2006}, {"year": 2005}, {"year": 2004}, {"year": 2003}, {"year": 2002}, {"year": 2001}, {"year": 2000}, {"year": 1999}, {"year": 1998}, {"year": 1997}, {"year": 1996}, {"year": 1995}, {"year": 1994}, {"year": 1993}, {"year": 1992}]},
{"country": "samoa", "years": [{"year": 2011}, {"year": 2010}, {"year": 2009}, {"year": 2008}, {"year": 2007}, {"year": 2006}, {"year": 2005}, {"year": 2004}, {"year": 2003}, {"year": 2002}, {"year": 2001}, {"year": 2000}, {"year": 1997}, {"year": 1996}, {"year": 1995}, {"year": 1994}, {"year": 1993}]},
{"country": "azerbaijan", "years": [{"year": 2017}, {"year": 2013}, {"year": 2012}, {"year": 2011}, {"year": 2010}, {"year": 2009}, {"year": 2008}, {"year": 2006}, {"year": 2005}, {"year": 2004}, {"year": 2003}, {"year": 2002}, {"year": 2001}, {"year": 2000}, {"year": 1997}, {"year": 1996}, {"year": 1995}]},
{"country": "republic-of-moldova", "years": [{"year": 2022}, {"year": 2021}, {"year": 2020}, {"year": 2019}, {"year": 2018}, {"year": 2014}, {"year": 2013}, {"year": 2009}, {"year": 2008}, {"year": 2007}, {"year": 2006}, {"year": 2005}, {"year": 2004}, {"year": 2003}, {"year": 2002}, {"year": 2001}, {"year": 2000}, {"year": 1995}, {"year": 1994}]},
{"country": "colombia", "years": [{"year": 2009}, {"year": 2007}, {"year": 1992}]},
{"country": "russian-federation", "years": [{"year": 2021}, {"year": 2020}, {"year": 2019}, {"year": 2018}, {"year": 2017}, {"year": 2016}, {"year": 2015}, {"year": 2014}, {"year": 2013}, {"year": 2012}, {"year": 2010}, {"year": 2009}, {"year": 2008}, {"year": 2007}, {"year": 2006}, {"year": 2005}, {"year": 2004}, {"year": 2003}, {"year": 2002}, {"year": 2001}, {"year": 2000}, {"year": 1999}, {"year": 1998}, {"year": 1997}, {"year": 1996}, {"year": 1995}, {"year": 1994}, {"year": 1993}, {"year": 1992}]},
{"country": "cyprus", "years": [{"year": 2022}, {"year": 2020}, {"year": 2018}, {"year": 2017}, {"year": 2016}, {"year": 2015}, {"year": 2014}, {"year": 2013}, {"year": 2012}, {"year": 2011}, {"year": 2010}, {"year": 2008}, {"year": 2007}, {"year": 2006}, {"year": 2005}, {"year": 2004}, {"year": 2003}, {"year": 2002}, {"year": 2001}, {"year": 2000}, {"year": 1999}, {"year": 1998}, {"year": 1997}, {"year": 1996}, {"year": 1995}, {"year": 1994}, {"year": 1993}]},
{"country": "benin", "years": [{"year": 2021}, {"year": 2003}, {"year": 1997}, {"year": 1994}, {"year": 1993}, {"year": 1992}]},
{"country": "thailand", "years": [{"year": 2011}, {"year": 2009}, {"year": 2004}, {"year": 2003}, {"year": 2002}, {"year": 2001}, {"year": 2000}, {"year": 1999}, {"year": 1998}, {"year": 1997}, {"year": 1996}, {"year": 1995}, {"year": 1994}, {"year": 1993}]},
{"country": "united-kingdom", "years": [{"year": 2021}, {"year": 2020}, {"year": 2019}, {"year": 2018}, {"year": 2017}, {"year": 2016}, {"year": 2015}, {"year": 2014}, {"year": 2013}, {"year": 2012}, {"year": 2011}, {"year": 2010}, {"year": 2009}, {"year": 2008}, {"year": 2007}, {"year": 2006}, {"year": 2005}, {"year": 2004}, {"year": 2003}, {"year": 2002}, {"year": 2001}, {"year": 2000}, {"year": 1999}, {"year": 1998}, {"year": 1997}, {"year": 1996}, {"year": 1995}, {"year": 1994}, {"year": 1993}, {"year": 1992}]},
{"country": "philippines", "years": [{"year": 2008}, {"year": 2006}, {"year": 2004}, {"year": 2003}, {"year": 2002}, {"year": 2001}, {"year": 2000}, {"year": 1998}, {"year": 1997}, {"year": 1996}, {"year": 1995}, {"year": 1994}, {"year": 1993}, {"year": 1992}]},
{"country": "malta", "years": [{"year": 2012}, {"year": 2011}, {"year": 2010}, {"year": 2009}, {"year": 2008}, {"year": 2007}, {"year": 2006}, {"year": 2005}, {"year": 2004}, {"year": 2003}, {"year": 2002}, {"year": 2001}, {"year": 2000}, {"year": 1999}, {"year": 1998}, {"year": 1997}, {"year": 1996}, {"year": 1995}, {"year": 1994}, {"year": 1993}, {"year": 1992}]},
{"country": "ukraine", "years": [{"year": 2022}, {"year": 2021}, {"year": 2020}, {"year": 2019}, {"year": 2018}, {"year": 2017}, {"year": 2016}, {"year": 2015}, {"year": 2014}, {"year": 2013}, {"year": 2012}, {"year": 2010}, {"year": 2009}, {"year": 2008}, {"year": 2007}, {"year": 2006}, {"year": 2005}, {"year": 2004}, {"year": 2003}, {"year": 2002}, {"year": 2001}, {"year": 2000}, {"year": 1999}, {"year": 1998}, {"year": 1997}, {"year": 1996}, {"year": 1995}, {"year": 1994}, {"year": 1993}, {"year": 1992}]},
{"country": "finland", "years": [{"year": 2022}, {"year": 2021}, {"year": 2020}, {"year": 2019}, {"year": 2018}, {"year": 2017}, {"year": 2016}, {"year": 2015}, {"year": 2014}, {"year": 2013}, {"year": 2012}, {"year": 2011}, {"year": 2010}, {"year": 2009}, {"year": 2008}, {"year": 2007}, {"year": 2006}, {"year": 2005}, {"year": 2004}, {"year": 2003}, {"year": 2002}, {"year": 2001}, {"year": 2000}, {"year": 1999}, {"year": 1998}, {"year": 1997}, {"year": 1996}, {"year": 1995}, {"year": 1994}, {"year": 1993}, {"year": 1992}]},
{"country": "cuba", "years": [{"year": 2006}, {"year": 2005}, {"year": 2004}, {"year": 2003}, {"year": 2002}, {"year": 2001}, {"year": 2000}, {"year": 1999}, {"year": 1998}, {"year": 1997}, {"year": 1996}, {"year": 1995}, {"year": 1994}, {"year": 1993}, {"year": 1992}]},
{"country": "poland", "years": [{"year": 2022}, {"year": 2021}, {"year": 2020}, {"year": 2019}, {"year": 2018}, {"year": 2017}, {"year": 2016}, {"year": 2015}, {"year": 2014}, {"year": 2013}, {"year": 2012}, {"year": 2011}, {"year": 2010}, {"year": 2009}, {"year": 2008}, {"year": 2007}, {"year": 2006}, {"year": 2005}, {"year": 2004}, {"year": 2003}, {"year": 2002}, {"year": 2001}, {"year": 2000}, {"year": 1999}, {"year": 1998}, {"year": 1997}, {"year": 1996}, {"year": 1995}, {"year": 1994}, {"year": 1993}, {"year": 1992}]},
{"country": "india", "years": [{"year": 2021}, {"year": 2020}, {"year": 2019}, {"year": 2018}, {"year": 2017}, {"year": 2016}, {"year": 2015}, {"year": 2014}, {"year": 2012}, {"year": 2011}, {"year": 2010}, {"year": 2009}, {"year": 2008}, {"year": 2007}, {"year": 2006}, {"year": 2005}, {"year": 2004}, {"year": 2003}, {"year": 2002}, {"year": 2001}, {"year": 2000}, {"year": 1999}, {"year": 1998}, {"year": 1997}, {"year": 1996}, {"year": 1995}, {"year": 1994}, {"year": 1993}, {"year": 1992}]},
{"country": "morocco", "years": []},
{"country": "united-republic-of-tanzania", "years": [{"year": 2005}, {"year": 2004}, {"year": 2003}, {"year": 2002}, {"year": 2001}, {"year": 1997}, {"year": 1996}, {"year": 1995}, {"year": 1994}, {"year": 1993}, {"year": 1992}]},
{"country": "ireland", "years": [{"year": 2022}, {"year": 2021}, {"year": 2019}, {"year": 2017}, {"year": 2014}, {"year": 2013}, {"year": 2012}, {"year": 2011}, {"year": 2010}, {"year": 2009}, {"year": 2008}, {"year": 2007}, {"year": 2006}, {"year": 2005}, {"year": 2004}, {"year": 2003}, {"year": 2002}, {"year": 2001}, {"year": 2000}, {"year": 1999}, {"year": 1998}, {"year": 1997}, {"year": 1996}, {"year": 1995}, {"year": 1994}, {"year": 1993}, {"year": 1992}]},
{"country": "turkey", "years": [{"year": 2021}, {"year": 2020}, {"year": 2019}, {"year": 2018}, {"year": 2017}, {"year": 2016}, {"year": 2014}, {"year": 2013}, {"year": 2012}, {"year": 2010}, {"year": 2008}, {"year": 2007}, {"year": 2006}, {"year": 2005}, {"year": 2004}, {"year": 2003}, {"year": 2002}, {"year": 2001}, {"year": 2000}, {"year": 1999}, {"year": 1998}, {"year": 1997}, {"year": 1996}, {"year": 1995}, {"year": 1994}, {"year": 1993}, {"year": 1992}]},
{"country": "brunei-darussalam", "years": [{"year": 2007}, {"year": 2006}, {"year": 2003}, {"year": 2002}, {"year": 1997}, {"year": 1996}]},
{"country": "trinidad-and-tobago", "years": [{"year": 2014}, {"year": 2013}, {"year": 2012}, {"year": 2010}, {"year": 2006}, {"year": 2005}, {"year": 2004}, {"year": 2003}, {"year": 2002}, {"year": 2000}, {"year": 1999}, {"year": 1996}, {"year": 1995}, {"year": 1993}]},
{"country": "denmark", "years": [{"year": 2021}, {"year": 2020}, {"year": 2019}, {"year": 2014}, {"year": 2013}, {"year": 2012}, {"year": 2011}, {"year": 2010}, {"year": 2009}, {"year": 2008}, {"year": 2007}, {"year": 2006}, {"year": 2005}, {"year": 2004}, {"year": 2003}, {"year": 2002}, {"year": 2001}, {"year": 2000}, {"year": 1999}, {"year": 1998}, {"year": 1997}, {"year": 1996}, {"year": 1995}, {"year": 1994}, {"year": 1993}, {"year": 1992}]},
{"country": "ghana", "years": [{"year": 2007}, {"year": 2002}]},
{"country": "belarus", "years": [{"year": 2022}, {"year": 2021}, {"year": 2020}, {"year": 2018}, {"year": 2017}, {"year": 2015}, {"year": 2014}, {"year": 2013}, {"year": 2012}, {"year": 2011}, {"year": 2010}, {"year": 2009}, {"year": 2008}, {"year": 2007}, {"year": 2006}, {"year": 2005}, {"year": 2004}, {"year": 2003}, {"year": 2002}, {"year": 2001}, {"year": 2000}, {"year": 1999}, {"year": 1998}, {"year": 1997}, {"year": 1996}, {"year": 1995}, {"year": 1994}, {"year": 1993}, {"year": 1992}]},
{"country": "latvia", "years": [{"year": 2022}, {"year": 2021}, {"year": 2020}, {"year": 2019}, {"year": 2018}, {"year": 2017}, {"year": 2016}, {"year": 2015}, {"year": 2014}, {"year": 2013}, {"year": 2012}, {"year": 2010}, {"year": 2009}, {"year": 2008}, {"year": 2007}, {"year": 2006}, {"year": 2005}, {"year": 2004}, {"year": 2003}, {"year": 2002}, {"year": 2001}, {"year": 2000}, {"year": 1999}, {"year": 1998}, {"year": 1996}, {"year": 1995}]},
{"country": "democratic-republic-of-the-congo", "years": [{"year": 2004}, {"year": 2002}]},
{"country": "monaco", "years": [{"year": 2021}, {"year": 2015}, {"year": 2012}, {"year": 2010}, {"year": 2009}, {"year": 2008}, {"year": 2007}, {"year": 2006}, {"year": 2005}, {"year": 2004}, {"year": 2003}, {"year": 2002}, {"year": 2001}, {"year": 2000}, {"year": 1999}, {"year": 1998}, {"year": 1997}, {"year": 1996}, {"year": 1995}]},
{"country": "congo", "years": []},
{"country": "togo", "years": [{"year": 2007}, {"year": 2006}, {"year": 2000}]},
{"country": "viet-nam", "years": [{"year": 2022}, {"year": 2016}, {"year": 2014}, {"year": 2013}, {"year": 2012}, {"year": 2011}, {"year": 2010}, {"year": 2009}, {"year": 2008}, {"year": 2007}, {"year": 2006}, {"year": 2005}, {"year": 2004}, {"year": 2003}, {"year": 2002}, {"year": 2001}, {"year": 2000}, {"year": 1999}, {"year": 1998}, {"year": 1997}, {"year": 1996}, {"year": 1995}, {"year": 1994}]},
{"country": "sweden", "years": [{"year": 2021}, {"year": 2020}, {"year": 2019}, {"year": 2018}, {"year": 2017}, {"year": 2016}, {"year": 2015}, {"year": 2014}, {"year": 2013}, {"year": 2012}, {"year": 2011}, {"year": 2009}, {"year": 2008}, {"year": 2007}, {"year": 2006}, {"year": 2005}, {"year": 2004}, {"year": 2003}, {"year": 2002}, {"year": 2001}, {"year": 2000}, {"year": 1999}, {"year": 1998}, {"year": 1997}, {"year": 1996}, {"year": 1995}, {"year": 1994}, {"year": 1993}, {"year": 1992}]},
{"country": "chile", "years": [{"year": 2022}, {"year": 2021}, {"year": 2020}, {"year": 2016}, {"year": 2015}, {"year": 2014}, {"year": 2013}, {"year": 2012}, {"year": 2011}, {"year": 2010}, {"year": 2009}, {"year": 2008}, {"year": 2007}, {"year": 2006}, {"year": 2005}, {"year": 2004}, {"year": 2003}, {"year": 2002}, {"year": 2001}, {"year": 2000}, {"year": 1999}, {"year": 1998}, {"year": 1997}, {"year": 1996}, {"year": 1995}, {"year": 1994}, {"year": 1993}, {"year": 1992}]},
{"country": "lesotho", "years": [{"year": 2005}, {"year": 2004}, {"year": 2002}, {"year": 2001}, {"year": 1998}, {"year": 1992}]},
{"country": "japan", "years": [{"year": 2022}, {"year": 2021}, {"year": 2020}, {"year": 2019}, {"year": 2018}, {"year": 2017}, {"year": 2016}, {"year": 2015}, {"year": 2014}, {"year": 2013}, {"year": 2012}, {"year": 2011}, {"year": 2010}, {"year": 2009}, {"year": 2008}, {"year": 2007}, {"year": 2006}, {"year": 2005}, {"year": 2004}, {"year": 2003}, {"year": 2002}, {"year": 2001}, {"year": 2000}, {"year": 1999}, {"year": 1998}, {"year": 1997}, {"year": 1996}, {"year": 1995}, {"year": 1994}, {"year": 1993}, {"year": 1992}]},
{"country": "marshall-islands", "years": [{"year": 2005}, {"year": 2004}, {"year": 2003}, {"year": 2002}, {"year": 2001}, {"year": 2000}, {"year": 1999}, {"year": 1996}, {"year": 1994}, {"year": 1993}]},
{"country": "gambia", "years": [{"year": 2006}, {"year": 2004}, {"year": 2002}, {"year": 2001}]},
{"country": "barbados", "years": [{"year": 2003}, {"year": 2002}, {"year": 2001}, {"year": 2000}, {"year": 1998}, {"year": 1995}, {"year": 1994}, {"year": 1993}, {"year": 1992}]},
{"country": "slovenia", "years": [{"year": 2021}, {"year": 2020}, {"year": 2019}, {"year": 2018}, {"year": 2017}, {"year": 2015}, {"year": 2014}, {"year": 2013}, {"year": 2012}, {"year": 2011}, {"year": 2009}, {"year": 2008}, {"year": 2007}, {"year": 2006}, {"year": 2005}, {"year": 2004}, {"year": 2003}, {"year": 2002}, {"year": 2001}, {"year": 2000}, {"year": 1999}, {"year": 1998}, {"year": 1997}, {"year": 1996}, {"year": 1995}, {"year": 1994}, {"year": 1993}, {"year": 1992}]},
{"country": "afghanistan", "years": [{"year": 1993}]},
{"country": "maldives", "years": [{"year": 2021}, {"year": 2011}, {"year": 2007}, {"year": 2006}, {"year": 2005}, {"year": 2004}, {"year": 2003}, {"year": 2002}, {"year": 2001}, {"year": 2000}, {"year": 1999}, {"year": 1998}, {"year": 1997}, {"year": 1996}, {"year": 1995}, {"year": 1994}, {"year": 1993}, {"year": 1992}]},
{"country": "china", "years": [{"year": 2022}, {"year": 2021}, {"year": 2020}, {"year": 2019}, {"year": 2018}, {"year": 2017}, {"year": 2016}, {"year": 2015}, {"year": 2014}, {"year": 2013}, {"year": 2012}, {"year": 2011}, {"year": 2009}, {"year": 2008}, {"year": 2007}, {"year": 2006}, {"year": 1996}, {"year": 1995}, {"year": 1994}, {"year": 1993}, {"year": 1992}]},
{"country": "brazil", "years": [{"year": 2018}, {"year": 2017}, {"year": 2016}, {"year": 2015}, {"year": 2014}, {"year": 2013}, {"year": 2012}, {"year": 2010}, {"year": 2009}, {"year": 2008}, {"year": 2007}, {"year": 2006}, {"year": 2005}, {"year": 2004}, {"year": 2003}, {"year": 2002}, {"year": 2001}, {"year": 2000}, {"year": 1999}, {"year": 1998}, {"year": 1997}, {"year": 1996}, {"year": 1995}, {"year": 1994}, {"year": 1993}, {"year": 1992}]},
{"country": "dominican-republic", "years": [{"year": 2018}, {"year": 2010}, {"year": 1999}, {"year": 1998}, {"year": 1996}, {"year": 1993}]},
{"country": "swaziland", "years": [{"year": 2008}, {"year": 2007}, {"year": 2006}]},
{"country": "netherlands", "years": [{"year": 2022}, {"year": 2021}, {"year": 2020}, {"year": 2019}, {"year": 2018}, {"year": 2017}, {"year": 2016}, {"year": 2015}, {"year": 2014}, {"year": 2013}, {"year": 2012}, {"year": 2011}, {"year": 2010}, {"year": 2009}, {"year": 2008}, {"year": 2007}, {"year": 2006}, {"year": 2005}, {"year": 2004}, {"year": 2003}, {"year": 2002}, {"year": 2001}, {"year": 2000}, {"year": 1999}, {"year": 1998}, {"year": 1997}, {"year": 1996}, {"year": 1995}, {"year": 1994}, {"year": 1993}, {"year": 1992}]},
{"country": "chad", "years": [{"year": 1994}, {"year": 1993}]},
{"country": "syrian-arab-republic", "years": []},
{"country": "georgia", "years": [{"year": 2007}, {"year": 2006}, {"year": 2005}, {"year": 2004}, {"year": 2003}, {"year": 2002}, {"year": 2001}, {"year": 2000}, {"year": 1999}, {"year": 1998}, {"year": 1997}, {"year": 1996}, {"year": 1994}, {"year": 1993}, {"year": 1992}]},
{"country": "niger", "years": [{"year": 2005}, {"year": 2001}, {"year": 2000}, {"year": 1997}, {"year": 1994}, {"year": 1993}, {"year": 1992}]},
{"country": "united-arab-emirates", "years": []},
{"country": "indonesia", "years": [{"year": 2008}, {"year": 2007}, {"year": 2005}, {"year": 2004}, {"year": 2003}, {"year": 2002}, {"year": 2001}, {"year": 2000}, {"year": 1999}, {"year": 1998}, {"year": 1997}, {"year": 1996}, {"year": 1995}, {"year": 1994}, {"year": 1993}, {"year": 1992}]},
{"country": "mauritania", "years": [{"year": 1994}, {"year": 1993}]},
{"country": "tuvalu", "years": [{"year": 2006}, {"year": 2005}, {"year": 2004}, {"year": 2003}, {"year": 2002}, {"year": 2001}, {"year": 2000}, {"year": 1999}, {"year": 1998}, {"year": 1997}, {"year": 1996}, {"year": 1995}, {"year": 1994}, {"year": 1993}, {"year": 1992}]},
{"country": "sri-lanka", "years": [{"year": 1995}, {"year": 1994}, {"year": 1993}, {"year": 1992}]},
{"country": "kuwait", "years": [{"year": 2005}]},
{"country": "switzerland", "years": [{"year": 2022}, {"year": 2021}, {"year": 2020}, {"year": 2019}, {"year": 2018}, {"year": 2017}, {"year": 2016}, {"year": 2014}, {"year": 2013}, {"year": 2012}, {"year": 2010}, {"year": 2009}, {"year": 2008}, {"year": 2007}, {"year": 2006}, {"year": 2005}, {"year": 2004}, {"year": 2003}, {"year": 2002}, {"year": 2001}, {"year": 2000}, {"year": 1999}, {"year": 1998}, {"year": 1997}, {"year": 1996}, {"year": 1995}, {"year": 1994}, {"year": 1993}, {"year": 1992}]},
{"country": "haiti", "years": [{"year": 2006}, {"year": 2002}, {"year": 2001}]},
{"country": "burkina-faso", "years": [{"year": 2021}, {"year": 2006}, {"year": 2005}, {"year": 2004}, {"year": 2003}, {"year": 2002}, {"year": 2001}, {"year": 2000}, {"year": 1999}, {"year": 1995}, {"year": 1994}, {"year": 1993}]},
{"country": "albania", "years": [{"year": 2017}, {"year": 2016}, {"year": 2015}, {"year": 2013}, {"year": 2012}, {"year": 2011}, {"year": 2009}, {"year": 2007}, {"year": 2006}, {"year": 2005}, {"year": 2004}, {"year": 2002}, {"year": 2000}, {"year": 1995}, {"year": 1992}]},
{"country": "san-marino", "years": [{"year": 2022}, {"year": 2013}, {"year": 2012}, {"year": 2011}, {"year": 2010}, {"year": 2009}, {"year": 2007}, {"year": 2006}, {"year": 2005}, {"year": 2004}, {"year": 2003}, {"year": 2001}, {"year": 2000}, {"year": 1999}, {"year": 1998}, {"year": 1997}]},
{"country": "canada", "years": [{"year": 2022}, {"year": 2021}, {"year": 2020}, {"year": 2019}, {"year": 2018}, {"year": 2017}, {"year": 2016}, {"year": 2015}, {"year": 2014}, {"year": 2012}, {"year": 2010}, {"year": 2009}, {"year": 2008}, {"year": 2007}, {"year": 2006}, {"year": 2005}, {"year": 2004}, {"year": 2003}, {"year": 2002}, {"year": 2001}, {"year": 2000}, {"year": 1999}, {"year": 1998}, {"year": 1997}, {"year": 1996}, {"year": 1995}, {"year": 1994}, {"year": 1993}, {"year": 1992}]},
{"country": "bahamas", "years": [{"year": 2011}, {"year": 2006}, {"year": 2004}, {"year": 2003}, {"year": 2001}, {"year": 1995}, {"year": 1994}]},
{"country": "nepal", "years": [{"year": 2012}, {"year": 2004}, {"year": 2003}, {"year": 2002}, {"year": 2001}, {"year": 2000}, {"year": 1999}, {"year": 1997}, {"year": 1995}, {"year": 1994}, {"year": 1993}, {"year": 1992}]},
{"country": "jamaica", "years": [{"year": 2021}, {"year": 2014}, {"year": 2012}, {"year": 2006}, {"year": 2005}, {"year": 2004}, {"year": 2003}, {"year": 2002}, {"year": 2001}, {"year": 2000}, {"year": 1999}, {"year": 1997}, {"year": 1995}, {"year": 1994}, {"year": 1993}, {"year": 1992}]},
{"country": "algeria", "years": []},
{"country": "sudan", "years": []},
{"country": "new-zealand", "years": [{"year": 2022}, {"year": 2021}, {"year": 2009}, {"year": 2008}, {"year": 2007}, {"year": 2006}, {"year": 2005}, {"year": 2004}, {"year": 2003}, {"year": 2002}, {"year": 2001}, {"year": 2000}, {"year": 1999}, {"year": 1998}, {"year": 1997}, {"year": 1996}, {"year": 1995}, {"year": 1994}, {"year": 1993}, {"year": 1992}]},
{"country": "yemen", "years": []},
{"country": "bolivarian-republic-of-venezuela", "years": [{"year": 2002}, {"year": 1997}]},
{"country": "italy", "years": [{"year": 2022}, {"year": 2021}, {"year": 2020}, {"year": 2019}, {"year": 2018}, {"year": 2017}, {"year": 2016}, {"year": 2014}, {"year": 2013}, {"year": 2009}, {"year": 2008}, {"year": 2007}, {"year": 2006}, {"year": 2005}, {"year": 2004}, {"year": 2003}, {"year": 2002}, {"year": 2001}, {"year": 2000}, {"year": 1999}, {"year": 1998}, {"year": 1997}, {"year": 1996}, {"year": 1995}, {"year": 1994}, {"year": 1993}, {"year": 1992}]},
{"country": "namibia", "years": [{"year": 2007}, {"year": 2006}, {"year": 2005}, {"year": 2004}, {"year": 2003}, {"year": 2002}, {"year": 1996}, {"year": 1995}, {"year": 1992}]},
{"country": "central-african-republic", "years": [{"year": 1995}]},
{"country": "uganda", "years": []},
{"country": "cape-verde", "years": []},
{"country": "botswana", "years": [{"year": 2000}]},
{"country": "portugal", "years": [{"year": 2022}, {"year": 2021}, {"year": 2020}, {"year": 2019}, {"year": 2018}, {"year": 2017}, {"year": 2016}, {"year": 2015}, {"year": 2014}, {"year": 2013}, {"year": 2012}, {"year": 2011}, {"year": 2010}, {"year": 2009}, {"year": 2008}, {"year": 2007}, {"year": 2006}, {"year": 2005}, {"year": 2004}, {"year": 2003}, {"year": 2002}, {"year": 2001}, {"year": 2000}, {"year": 1999}, {"year": 1998}, {"year": 1997}, {"year": 1996}, {"year": 1995}, {"year": 1994}, {"year": 1993}, {"year": 1992}]},
{"country": "iraq", "years": []},
{"country": "djibouti", "years": [{"year": 2007}, {"year": 2006}, {"year": 2005}, {"year": 2003}, {"year": 2001}]},
{"country": "liberia", "years": []},
{"country": "kiribati", "years": [{"year": 2006}, {"year": 2005}, {"year": 2004}, {"year": 2003}, {"year": 2002}, {"year": 2001}, {"year": 2000}, {"year": 1997}]},
{"country": "lao-peoples-democratic-republic", "years": [{"year": 2009}, {"year": 2002}]},
{"country": "liechtenstein", "years": [{"year": 2022}, {"year": 2021}, {"year": 2020}, {"year": 2019}, {"year": 2018}, {"year": 2017}, {"year": 2016}, {"year": 2015}, {"year": 2012}, {"year": 2011}, {"year": 2010}, {"year": 2009}, {"year": 2008}, {"year": 2007}, {"year": 2006}, {"year": 2005}, {"year": 2004}, {"year": 2003}, {"year": 2002}, {"year": 2001}, {"year": 2000}, {"year": 1999}, {"year": 1998}, {"year": 1997}, {"year": 1996}, {"year": 1995}, {"year": 1994}, {"year": 1993}, {"year": 1992}]},
{"country": "saint-lucia", "years": [{"year": 2006}, {"year": 2005}, {"year": 2004}, {"year": 2002}, {"year": 1996}, {"year": 1994}, {"year": 1993}, {"year": 1992}]},
{"country": "burundi", "years": [{"year": 2008}, {"year": 2005}, {"year": 2004}]},
{"country": "romania", "years": [{"year": 2022}, {"year": 2021}, {"year": 2020}, {"year": 2019}, {"year": 2018}, {"year": 2017}, {"year": 2016}, {"year": 2015}, {"year": 2014}, {"year": 2013}, {"year": 2012}, {"year": 2010}, {"year": 2009}, {"year": 2008}, {"year": 2007}, {"year": 2006}, {"year": 2005}, {"year": 2004}, {"year": 2003}, {"year": 2002}, {"year": 2001}, {"year": 2000}, {"year": 1999}, {"year": 1998}, {"year": 1997}, {"year": 1996}, {"year": 1995}, {"year": 1994}, {"year": 1993}, {"year": 1992}]},
{"country": "bosnia-and-herzegovina", "years": [{"year": 2022}, {"year": 2021}, {"year": 2018}, {"year": 2017}, {"year": 2016}, {"year": 2015}, {"year": 2013}, {"year": 2012}, {"year": 2010}, {"year": 2009}, {"year": 2008}, {"year": 2007}, {"year": 2006}, {"year": 2005}, {"year": 2004}, {"year": 2002}, {"year": 2001}, {"year": 2000}, {"year": 1999}]},
{"country": "bangladesh", "years": [{"year": 2010}, {"year": 2008}, {"year": 2007}, {"year": 2006}, {"year": 2005}, {"year": 2004}, {"year": 2003}, {"year": 2002}, {"year": 2001}, {"year": 2000}, {"year": 1999}, {"year": 1998}]},
{"country": "czech-republic", "years": [{"year": 2022}, {"year": 2021}, {"year": 2020}, {"year": 2019}, {"year": 2018}, {"year": 2017}, {"year": 2016}, {"year": 2015}, {"year": 2014}, {"year": 2013}, {"year": 2012}, {"year": 2011}, {"year": 2010}, {"year": 2008}, {"year": 2007}, {"year": 2006}, {"year": 2005}, {"year": 2004}, {"year": 2003}, {"year": 2002}, {"year": 2001}, {"year": 2000}, {"year": 1999}, {"year": 1998}, {"year": 1997}, {"year": 1996}, {"year": 1995}, {"year": 1994}, {"year": 1993}, {"year": 1992}]},
{"country": "gabon", "years": [{"year": 2006}, {"year": 2004}, {"year": 1995}]},
{"country": "nigeria", "years": []},
{"country": "ecuador", "years": [{"year": 2011}, {"year": 2005}, {"year": 2003}, {"year": 2002}, {"year": 2001}, {"year": 2000}, {"year": 1999}, {"year": 1998}, {"year": 1996}, {"year": 1994}]},
{"country": "greece", "years": [{"year": 2022}, {"year": 2021}, {"year": 2020}, {"year": 2019}, {"year": 2018}, {"year": 2017}, {"year": 2016}, {"year": 2015}, {"year": 2014}, {"year": 2012}, {"year": 2011}, {"year": 2010}, {"year": 2009}, {"year": 2007}, {"year": 2006}, {"year": 2005}, {"year": 2004}, {"year": 2003}, {"year": 2002}, {"year": 2001}, {"year": 2000}, {"year": 1999}, {"year": 1998}, {"year": 1997}, {"year": 1996}, {"year": 1995}, {"year": 1994}, {"year": 1993}, {"year": 1992}]},
{"country": "nauru", "years": [{"year": 2015}, {"year": 2012}, {"year": 2009}, {"year": 2008}, {"year": 2007}, {"year": 2006}, {"year": 2005}, {"year": 2003}, {"year": 2002}, {"year": 2001}, {"year": 2000}]},
{"country": "bhutan", "years": [{"year": 2015}, {"year": 2013}, {"year": 2012}, {"year": 2010}, {"year": 2008}, {"year": 2007}, {"year": 2006}, {"year": 2003}, {"year": 2002}, {"year": 2001}, {"year": 2000}, {"year": 1999}, {"year": 1998}, {"year": 1997}, {"year": 1996}, {"year": 1995}, {"year": 1994}, {"year": 1993}, {"year": 1992}]},
{"country": "comoros", "years": [{"year": 2012}, {"year": 2009}, {"year": 2005}, {"year": 2004}, {"year": 2002}, {"year": 2001}, {"year": 1993}]},
{"country": "zambia", "years": [{"year": 2006}, {"year": 2005}, {"year": 2004}, {"year": 2002}, {"year": 2001}, {"year": 2000}, {"year": 1999}]},
{"country": "estonia", "years": [{"year": 2019}, {"year": 2015}, {"year": 2014}, {"year": 2013}, {"year": 2012}, {"year": 2011}, {"year": 2010}, {"year": 2009}, {"year": 2008}, {"year": 2007}, {"year": 2006}, {"year": 2005}, {"year": 2004}, {"year": 2003}, {"year": 2002}, {"year": 2001}, {"year": 2000}, {"year": 1999}, {"year": 1998}, {"year": 1997}, {"year": 1996}, {"year": 1995}, {"year": 1994}]},
{"country": "mali", "years": [{"year": 2006}]},
{"country": "malawi", "years": [{"year": 2004}, {"year": 2003}, {"year": 2002}, {"year": 2001}, {"year": 2000}, {"year": 1993}]},
{"country": "guinea", "years": []},
{"country": "panama", "years": [{"year": 2008}, {"year": 2006}, {"year": 2002}, {"year": 2001}, {"year": 2000}, {"year": 1994}, {"year": 1992}]},
{"country": "cambodia", "years": [{"year": 2014}, {"year": 2013}, {"year": 2012}, {"year": 2010}, {"year": 2009}, {"year": 2004}, {"year": 2003}, {"year": 2001}, {"year": 2000}, {"year": 1999}]},
{"country": "somalia", "years": []},
{"country": "saint-kitts-and-nevis", "years": [{"year": 2005}, {"year": 2001}, {"year": 2000}, {"year": 1995}]},
{"country": "saint-vincent-and-the-grenadines", "years": [{"year": 2022}, {"year": 2008}, {"year": 2006}, {"year": 2005}, {"year": 2004}, {"year": 2001}, {"year": 1995}, {"year": 1993}]},
{"country": "papua-new-guinea", "years": [{"year": 1998}, {"year": 1997}, {"year": 1995}, {"year": 1994}, {"year": 1993}, {"year": 1992}]},
{"country": "nicaragua", "years": [{"year": 2006}, {"year": 2005}, {"year": 1992}]},
{"country": "democratic-peoples-republic-of-korea", "years": []},
{"country": "argentina", "years": [{"year": 2021}, {"year": 2020}, {"year": 2019}, {"year": 2018}, {"year": 2017}, {"year": 2016}, {"year": 2013}, {"year": 2012}, {"year": 2011}, {"year": 2010}, {"year": 2009}, {"year": 2008}, {"year": 2007}, {"year": 2005}, {"year": 2004}, {"year": 2003}, {"year": 2002}, {"year": 2001}, {"year": 2000}, {"year": 1999}, {"year": 1998}, {"year": 1997}, {"year": 1996}, {"year": 1995}, {"year": 1994}, {"year": 1993}, {"year": 1992}]},
{"country": "tunisia", "years": [{"year": 2009}, {"year": 1992}]},
{"country": "luxembourg", "years": [{"year": 2021}, {"year": 2020}, {"year": 2019}, {"year": 2018}, {"year": 2017}, {"year": 2016}, {"year": 2014}, {"year": 2013}, {"year": 2012}, {"year": 2007}, {"year": 2006}, {"year": 2005}, {"year": 2003}, {"year": 2002}, {"year": 2001}, {"year": 2000}, {"year": 1999}, {"year": 1998}, {"year": 1997}, {"year": 1996}, {"year": 1995}, {"year": 1994}, {"year": 1993}, {"year": 1992}]},
{"country": "solomon-islands", "years": [{"year": 2015}, {"year": 2010}, {"year": 2008}, {"year": 2006}, {"year": 2005}, {"year": 2004}, {"year": 2003}, {"year": 2002}, {"year": 2001}, {"year": 2000}, {"year": 1998}, {"year": 1997}, {"year": 1994}, {"year": 1992}]},
{"country": "kyrgyzstan", "years": [{"year": 2009}, {"year": 2007}, {"year": 2005}, {"year": 2004}, {"year": 2003}, {"year": 1995}]},
{"country": "spain", "years": [{"year": 2022}, {"year": 2020}, {"year": 2019}, {"year": 2018}, {"year": 2017}, {"year": 2016}, {"year": 2015}, {"year": 2014}, {"year": 2013}, {"year": 2012}, {"year": 2011}, {"year": 2010}, {"year": 2009}, {"year": 2008}, {"year": 2007}, {"year": 2006}, {"year": 2005}, {"year": 2004}, {"year": 2003}, {"year": 2002}, {"year": 2001}, {"year": 2000}, {"year": 1999}, {"year": 1998}, {"year": 1997}, {"year": 1996}, {"year": 1995}, {"year": 1994}, {"year": 1993}, {"year": 1992}]},
{"country": "turkmenistan", "years": [{"year": 2010}, {"year": 2005}, {"year": 2004}, {"year": 2000}, {"year": 1999}, {"year": 1998}, {"year": 1997}, {"year": 1996}, {"year": 1995}]},
{"country": "zimbabwe", "years": []},
{"country": "cote-divoire", "years": [{"year": 2002}, {"year": 1993}]},
{"country": "andorra", "years": [{"year": 2014}, {"year": 2012}, {"year": 2011}, {"year": 2009}, {"year": 2008}, {"year": 2006}, {"year": 2005}, {"year": 2004}, {"year": 2003}, {"year": 2002}, {"year": 2001}, {"year": 2000}, {"year": 1999}, {"year": 1998}, {"year": 1997}, {"year": 1996}, {"year": 1995}, {"year": 1994}]},
{"country": "guatemala", "years": [{"year": 2007}, {"year": 2006}, {"year": 2005}, {"year": 2004}, {"year": 2003}, {"year": 2002}, {"year": 2001}, {"year": 2000}, {"year": 1999}, {"year": 1998}, {"year": 1997}, {"year": 1996}]},
{"country": "pakistan", "years": [{"year": 2015}, {"year": 2014}, {"year": 2013}, {"year": 2012}, {"year": 2010}, {"year": 2008}, {"year": 2007}, {"year": 2006}, {"year": 2005}, {"year": 2004}, {"year": 2003}, {"year": 2002}, {"year": 2001}, {"year": 2000}, {"year": 1999}, {"year": 1998}, {"year": 1997}, {"year": 1996}, {"year": 1995}, {"year": 1994}, {"year": 1993}, {"year": 1992}]},
{"country": "croatia", "years": [{"year": 2014}, {"year": 2013}, {"year": 2012}, {"year": 2011}, {"year": 2010}, {"year": 2008}, {"year": 2007}, {"year": 2006}, {"year": 2005}, {"year": 2004}, {"year": 2003}, {"year": 2002}, {"year": 2001}, {"year": 2000}, {"year": 1999}, {"year": 1998}, {"year": 1997}, {"year": 1996}, {"year": 1994}, {"year": 1993}, {"year": 1992}]},
{"country": "kazakhstan", "years": [{"year": 2021}, {"year": 2019}, {"year": 2012}, {"year": 2011}, {"year": 2009}, {"year": 2008}, {"year": 2006}, {"year": 2005}, {"year": 2004}, {"year": 2003}, {"year": 2002}, {"year": 2001}, {"year": 2000}, {"year": 1999}, {"year": 1998}, {"year": 1997}, {"year": 1996}, {"year": 1995}, {"year": 1994}, {"year": 1992}]},
{"country": "cameroon", "years": [{"year": 1997}, {"year": 1996}, {"year": 1994}]},
{"country": "uruguay", "years": [{"year": 2022}, {"year": 2020}, {"year": 2019}, {"year": 2015}, {"year": 2014}, {"year": 2013}, {"year": 2012}, {"year": 2010}, {"year": 2002}, {"year": 2001}, {"year": 2000}, {"year": 1999}, {"year": 1998}]},
{"country": "equatorial-guinea", "years": []},
{"country": "armenia", "years": [{"year": 2018}, {"year": 2017}, {"year": 2016}, {"year": 2012}, {"year": 2009}, {"year": 2008}, {"year": 2007}, {"year": 2006}, {"year": 2005}, {"year": 2004}, {"year": 2003}, {"year": 2002}, {"year": 2001}, {"year": 2000}, {"year": 1999}, {"year": 1998}, {"year": 1997}, {"year": 1996}, {"year": 1995}, {"year": 1994}, {"year": 1993}]},
{"country": "madagascar", "years": [{"year": 2021}, {"year": 2000}, {"year": 1999}, {"year": 1998}, {"year": 1997}, {"year": 1996}, {"year": 1995}, {"year": 1993}]},
{"country": "bolivia", "years": [{"year": 2009}, {"year": 2008}, {"year": 2006}, {"year": 2005}, {"year": 2004}, {"year": 2003}, {"year": 2002}, {"year": 2001}, {"year": 2000}, {"year": 1999}, {"year": 1992}]},
{"country": "ethiopia", "years": [{"year": 1997}, {"year": 1996}, {"year": 1995}]},
{"country": "paraguay", "years": [{"year": 2022}, {"year": 2006}, {"year": 2005}, {"year": 2004}, {"year": 2003}, {"year": 2002}, {"year": 2001}, {"year": 2000}, {"year": 1999}, {"year": 1997}, {"year": 1996}, {"year": 1994}, {"year": 1993}, {"year": 1992}]},
{"country": "belgium", "years": [{"year": 2021}, {"year": 2020}, {"year": 2019}, {"year": 2018}, {"year": 2017}, {"year": 2015}, {"year": 2014}, {"year": 2013}, {"year": 2012}, {"year": 2011}, {"year": 2010}, {"year": 2009}, {"year": 2008}, {"year": 2007}, {"year": 2006}, {"year": 2005}, {"year": 2004}, {"year": 2003}, {"year": 2002}, {"year": 2001}, {"year": 2000}, {"year": 1999}, {"year": 1998}, {"year": 1997}, {"year": 1996}, {"year": 1995}, {"year": 1994}, {"year": 1993}, {"year": 1992}]}
]